MANIFEST.in
README.rst
setup.py
collective/__init__.py
collective.wtforms.egg-info/PKG-INFO
collective.wtforms.egg-info/SOURCES.txt
collective.wtforms.egg-info/dependency_links.txt
collective.wtforms.egg-info/entry_points.txt
collective.wtforms.egg-info/namespace_packages.txt
collective.wtforms.egg-info/not-zip-safe
collective.wtforms.egg-info/paster_plugins.txt
collective.wtforms.egg-info/requires.txt
collective.wtforms.egg-info/top_level.txt
collective/wtforms/.DS_Store
collective/wtforms/__init__.py
collective/wtforms/basicform.pt
collective/wtforms/configure.zcml
collective/wtforms/controlpanelform.pt
collective/wtforms/field.pt
collective/wtforms/form.pt
collective/wtforms/testing.py
collective/wtforms/views.py
collective/wtforms/locales/collective.wtforms.pot
collective/wtforms/locales/runi18ndude.sh
collective/wtforms/locales/wtforms.pot
collective/wtforms/locales/it/LC_MESSAGES/collective.wtforms.po
collective/wtforms/tests/__init__.py
collective/wtforms/tests/test.zcml
collective/wtforms/tests/test_form.py
docs/HISTORY.txt
docs/INSTALL.txt
docs/LICENSE.GPL
docs/LICENSE.txt