Metadata-Version: 1.0
Name: collective.wtforms
Version: 1.0a6
Summary: Plone wtforms integration
Home-page: http://github.com/collective/collective.wtforms
Author: Nathan Van Gheem
Author-email: vangheem@gmail.com
License: GPL
Keywords: forms plone wtforms
Platform: UNKNOWN
Classifier: Framework :: Plone
Classifier: Programming Language :: Python
